master/__init__.py
master/cli.py
master/logger.py
master/master.py
master/pass.py
master-0.2.5.dist-info/LICENSE
master-0.2.5.dist-info/METADATA
master-0.2.5.dist-info/WHEEL
master-0.2.5.dist-info/entry_points.txt
master-0.2.5.dist-info/top_level.txt
master-0.2.5.dist-info/RECORD
