Metadata-Version: 2.1
Name: master
Version: 0.2.5
Summary: Deterministic password generator
Home-page: https://github.com/jpedro/master
Download-URL: https://github.com/jpedro/master/tarball/master
Author: jpedro
Author-email: jpedro.barbosa@gmail.com
License: MIT
Keywords: deterministic password generator
Classifier: Development Status :: 3 - Alpha
Classifier: Intended Audience :: Developers
Classifier: Topic :: Software Development :: Build Tools
Classifier: License :: OSI Approved :: MIT License
Classifier: Programming Language :: Python :: 3
Requires-Python: >=3
License-File: LICENSE
